recipescraper.py
arljol_recipescraper-0.0.1.dist-info/LICENSE.txt
arljol_recipescraper-0.0.1.dist-info/METADATA
arljol_recipescraper-0.0.1.dist-info/WHEEL
arljol_recipescraper-0.0.1.dist-info/top_level.txt
arljol_recipescraper-0.0.1.dist-info/RECORD
