Metadata-Version: 2.2
Name: arljol_recipescraper
Version: 0.0.1
Summary: Package to scrape minecraft recipes to pandas dataframe.
Author-email: Artem Ljukshin <garo109696@gmail.com>
License: MIT License
Classifier: Programming Language :: Python :: 3
Classifier: Operating System :: OS Independent
Requires-Python: >=3.10
License-File: LICENSE.txt
Requires-Dist: requests>=2.32.3
Requires-Dist: beautifulsoup4>=4.12.3
Requires-Dist: pandas>=2.2.3
